boydem/__init__.py
boydem-0.0.0.dist-info/LICENCE
boydem-0.0.0.dist-info/METADATA
boydem-0.0.0.dist-info/WHEEL
boydem-0.0.0.dist-info/top_level.txt
boydem-0.0.0.dist-info/RECORD
