Metadata-Version: 2.1
Name: boydem
Version: 0.0.0
Summary: Simple Persistent Python Storage
Home-page: https://github.com/omrirz/boydem
Author: Omri Rozenzaft
Author-email: omrirz@gmail.com
License: UNKNOWN
Platform: UNKNOWN
Classifier: Programming Language :: Python :: 3
Classifier: License :: OSI Approved :: MIT License
Classifier: Operating System :: OS Independent
Requires-Python: >=3.6
Requires-Dist: dill
